lexpy/__init__.py
lexpy/_constants.py
lexpy/_utils.py
lexpy/dawg.py
lexpy/exceptions.py
lexpy/trie.py
lexpy/utils.py
lexpy/_base/__init__.py
lexpy/_base/automata.py
lexpy/_base/node.py
lexpy/tests/__init__.py
lexpy/tests/test_dawg.py
lexpy/tests/test_trie.py
lexpy/tests/test_word_count.py
lexpy-1.1.0.dist-info/LICENSE
lexpy-1.1.0.dist-info/METADATA
lexpy-1.1.0.dist-info/WHEEL
lexpy-1.1.0.dist-info/top_level.txt
lexpy-1.1.0.dist-info/RECORD
