Metadata-Version: 2.1
Name: lexpy
Version: 1.1.0
Summary: Python package for lexicon
Home-page: https://github.com/aosingh/lexpy
Author: Abhishek Singh
Author-email: abhishek.singh20141@gmail.com
Maintainer: Abhishek Singh
Maintainer-email: abhishek.singh20141@gmail.com
License: GNU GPLv3
Project-URL: Documentation, https://github.com/aosingh/lexpy
Project-URL: Source, https://github.com/aosingh/lexpy
Project-URL: Bug Tracker, https://github.com/aosingh/lexpy/issues
Project-URL: CI, https://github.com/aosingh/lexpy/actions
Project-URL: Release Notes, https://github.com/aosingh/lexpy/releases
Project-URL: License, https://github.com/aosingh/lexpy/blob/main/LICENSE
Keywords: trie,suffix-trees,lexicon,directed-acyclic-word-graph,dawg
Classifier: Development Status :: 5 - Production/Stable
Classifier: Intended Audience :: Education
Classifier: Intended Audience :: Developers
Classifier: Intended Audience :: Science/Research
Classifier: Topic :: Text Processing :: Linguistic
Classifier: Topic :: Text Processing :: Indexing
Classifier: License :: OSI Approved :: GNU General Public License v3 (GPLv3)
Classifier: Programming Language :: Python :: 3.7
Classifier: Programming Language :: Python :: 3.8
Classifier: Programming Language :: Python :: 3.9
Classifier: Programming Language :: Python :: 3.10
Classifier: Programming Language :: Python :: 3.11
Classifier: Programming Language :: Python :: 3.12
Classifier: Operating System :: POSIX :: Linux
Classifier: Operating System :: Unix
Classifier: Operating System :: Microsoft :: Windows
Classifier: Operating System :: MacOS
Requires-Python: >=3.7
License-File: LICENSE
